dn_bpl
